pyhide/__init__.py
pyhide/__main__.py
pyhide/cli.py
pyhide_obf-0.1.0.dist-info/METADATA
pyhide_obf-0.1.0.dist-info/WHEEL
pyhide_obf-0.1.0.dist-info/entry_points.txt
pyhide_obf-0.1.0.dist-info/RECORD
